nbiot/__init__.py
nbiot/module.py
nbiot/scan.py
nbiot/socket.py
nbiot-0.0.1.dist-info/LICENSE
nbiot-0.0.1.dist-info/METADATA
nbiot-0.0.1.dist-info/WHEEL
nbiot-0.0.1.dist-info/entry_points.txt
nbiot-0.0.1.dist-info/top_level.txt
nbiot-0.0.1.dist-info/RECORD
