Metadata-Version: 2.1
Name: nbiot
Version: 0.0.1
Summary: NB IoT Scanner and Coverage Tool
Home-page: https://github.com/pwitab/nbiot
Author: Henrik Palmlund Wahlgren @ Palmlund Wahlgren Innovative Technology AB
Author-email: henrik@pwit.se
License: BSD-3
Platform: UNKNOWN
Classifier: Development Status :: 3 - Alpha
Classifier: License :: OSI Approved :: BSD License
Classifier: Natural Language :: English
Classifier: Programming Language :: Python
Classifier: Programming Language :: Python :: 3
Classifier: Programming Language :: Python :: 3 :: Only
Classifier: Programming Language :: Python :: 3.6
Classifier: Topic :: Software Development :: Libraries
Requires-Python: >=3.6
Requires-Dist: click (==7.0)
Requires-Dist: pyserial (==3.4)
Requires-Dist: tabulate (==0.8.7)
